{
  "main": {
    "id": "90b37ad8ee5e800c",
    "type": "split",
    "children": [
      {
        "id": "dd92709f225fded0",
        "type": "tabs",
        "children": [
          {
            "id": "147f03921882c513",
            "type": "leaf",
            "pane-relief:history-v1": {
              "pos": 0,
              "stack": [
                {
                  "state": "{}",
                  "eState": "{}"
                }
              ]
            },
            "state": {
              "type": "markdown",
              "state": {
                "file": "Notes on the Multiverse/Inner/Alaturmen/Places/Central Alaturmen.md",
                "mode": "source",
                "source": true
              }
            }
          },
          {
            "id": "8880b2909535a532",
            "type": "leaf",
            "pane-relief:history-v1": {
              "pos": 0,
              "stack": [
                {
                  "state": "{}",
                  "eState": "{}"
                }
              ]
            },
            "state": {
              "type": "release-notes",
              "state": {
                "currentVersion": "1.2.8"
              }
            }
          },
          {
            "id": "6a7ac565ac681fc4",
            "type": "leaf",
            "pane-relief:history-v1": {
              "pos": 0,
              "stack": [
                {
                  "state": "{}",
                  "eState": "{}"
                }
              ]
            },
            "state": {
              "type": "markdown",
              "state": {
                "file": "Notes on the Multiverse/Inner/Alaturmen/Places/Northwestern Central/Regions of NWC/The Holyl'nds/North Littemotto.md",
                "mode": "source",
                "source": true
              }
            }
          }
        ],
        "currentTab": 1
      }
    ],
    "direction": "vertical"
  },
  "left": {
    "id": "f200fe8a1a80900b",
    "type": "split",
    "children": [
      {
        "id": "1ee778f2eb66d012",
        "type": "tabs",
        "children": [
          {
            "id": "470822c6e780fecc",
            "type": "leaf",
            "pane-relief:history-v1": {
              "pos": 0,
              "stack": [
                {
                  "state": "{}",
                  "eState": "{}"
                }
              ]
            },
            "state": {
              "type": "recent-files",
              "state": {}
            }
          },
          {
            "id": "471fab77001b02ee",
            "type": "leaf",
            "pane-relief:history-v1": {
              "pos": 0,
              "stack": [
                {
                  "state": "{}",
                  "eState": "{}"
                }
              ]
            },
            "state": {
              "type": "search",
              "state": {
                "query": "AF28",
                "matchingCase": false,
                "explainSearch": false,
                "collapseAll": false,
                "extraContext": false,
                "sortOrder": "alphabetical"
              }
            }
          },
          {
            "id": "8a09bf3a4e0bad9d",
            "type": "leaf",
            "pane-relief:history-v1": {
              "pos": 0,
              "stack": [
                {
                  "state": "{}",
                  "eState": "{}"
                }
              ]
            },
            "state": {
              "type": "file-explorer",
              "state": {
                "sortOrder": "alphabetical"
              }
            }
          },
          {
            "id": "a28b40f20a51ecec",
            "type": "leaf",
            "pane-relief:history-v1": {
              "pos": 0,
              "stack": [
                {
                  "state": "{}",
                  "eState": "{}"
                }
              ]
            },
            "state": {
              "type": "bookmarks",
              "state": {}
            }
          }
        ],
        "currentTab": 1
      }
    ],
    "direction": "horizontal",
    "width": 338.5,
    "collapsed": true
  },
  "right": {
    "id": "22b1fb456ad17b5a",
    "type": "split",
    "children": [
      {
        "id": "345ad8dc0249f6ff",
        "type": "tabs",
        "children": [
          {
            "id": "214128aa17851074",
            "type": "leaf",
            "pane-relief:history-v1": {
              "pos": 0,
              "stack": [
                {
                  "state": "{}",
                  "eState": "{}"
                }
              ]
            },
            "state": {
              "type": "backlink",
              "state": {
                "file": "Notes on the Multiverse/Inner/Alaturmen/Places/Central Alaturmen.md",
                "collapseAll": false,
                "extraContext": false,
                "sortOrder": "alphabetical",
                "showSearch": false,
                "searchQuery": "",
                "backlinkCollapsed": false,
                "unlinkedCollapsed": true
              }
            }
          },
          {
            "id": "a784ad59b314c9b4",
            "type": "leaf",
            "pane-relief:history-v1": {
              "pos": 0,
              "stack": [
                {
                  "state": "{}",
                  "eState": "{}"
                }
              ]
            },
            "state": {
              "type": "outgoing-link",
              "state": {
                "file": "Notes on the Multiverse/Inner/Alaturmen/Places/Central Alaturmen.md",
                "linksCollapsed": false,
                "unlinkedCollapsed": true
              }
            }
          },
          {
            "id": "60736712cabd0795",
            "type": "leaf",
            "pane-relief:history-v1": {
              "pos": 0,
              "stack": [
                {
                  "state": "{}",
                  "eState": "{}"
                }
              ]
            },
            "state": {
              "type": "tag",
              "state": {
                "sortOrder": "frequency",
                "useHierarchy": true
              }
            }
          },
          {
            "id": "f44a3da8351e916d",
            "type": "leaf",
            "pane-relief:history-v1": {
              "pos": 0,
              "stack": [
                {
                  "state": "{}",
                  "eState": "{}"
                }
              ]
            },
            "state": {
              "type": "outline",
              "state": {
                "file": "Notes on the Multiverse/Inner/Alaturmen/Places/Central Alaturmen.md"
              }
            }
          },
          {
            "id": "017b0162b76e109a",
            "type": "leaf",
            "pane-relief:history-v1": {
              "pos": 0,
              "stack": [
                {
                  "state": "{}",
                  "eState": "{}"
                }
              ]
            },
            "state": {
              "type": "advanced-tables-toolbar",
              "state": {}
            }
          }
        ],
        "currentTab": 4
      }
    ],
    "direction": "horizontal",
    "width": 300,
    "collapsed": true
  },
  "left-ribbon": {
    "hiddenItems": {
      "switcher:Open quick switcher": false,
      "graph:Open graph view": false,
      "canvas:Create new canvas": false,
      "daily-notes:Open today's daily note": false,
      "templates:Insert template": false,
      "command-palette:Open command palette": false,
      "workspaces:Manage workspace layouts": false,
      "table-editor-obsidian:Advanced Tables Toolbar": false
    }
  },
  "active": "8880b2909535a532",
  "lastOpenFiles": [
    "Notes on the Multiverse/Inner/Alaturmen/Places/Northwestern Central/Regions of NWC/The Holyl'nds/North Littemotto.md",
    "Notes on the Multiverse/Inner/Alaturmen/Places/Central Alaturmen.md",
    "Notes on the Multiverse/Inner/Alaturmen/Places/Southwestern Central/Regions of SWC/Kailkeep/Kailkeep.md",
    "Notes on the Multiverse/Inner/Alaturmen/About People/Nations/The Democratic Combine of Peoples/Factions/Knights in Red/Knights in Red.md",
    "Notes on the Multiverse/Inner/Alaturmen/About People/Nations/Lands of Tetrimoc/Lands of Tetrimoc.md",
    "Notes on the Multiverse/Inner/Alaturmen/About People/Nations/Lands of Tetrimoc/Factions/Golden Merchant's Company.md",
    "Notes on the Multiverse/Inner/Alaturmen/About People/Nations/Lands of Tetrimoc/Factions/Tetramocal Congregation.md",
    "Notes on the Multiverse/Inner/Alaturmen/About People/Nations/Lands of Tetrimoc/Local Lore/First Invasion of Orcus.md",
    "Notes on the Multiverse/Inner/Alaturmen/About People/Nations/Lands of Tetrimoc/Local Lore/Tetrimoc's Tournament of Glory.md",
    "Notes on the Multiverse/Inner/Alaturmen/About People/Nations/Holyl'nds/The Church of the White Flame.md",
    "Notes on the Multiverse/Inner/Alaturmen/About People/Nations/Lands of Tetrimoc/Factions/Golden Claws.md",
    "Notes on the Multiverse/Inner/Alaturmen/About People/Nations/Lands of Tetrimoc/Factions/Cobalt's Thieves.md",
    "Notes on the Multiverse/Inner/Alaturmen/About People/Nations/Lands of Tetrimoc/Factions/Barthalmule's Thieves.md",
    "Notes on the Multiverse/Inner/Alaturmen/About People/Nations/Lands of Tetrimoc/Factions/Agrandica's Thieves.md",
    "Lake of Eternal Life.md",
    "Notes on the Multiverse/Big Lore/Languages/Languages.md",
    "MEDIA/MEDIA.md",
    "Game Notes/Prenotes/Prenotes.md",
    "Game Notes/NPCs/NPCs.md",
    "Game Notes/Mechanics/Homebrew Weapons/Weapons of Alaturmen.md",
    "Game Notes/Mechanics/Homebrew Weapons/Custom Weapon Mechanics.md",
    "Game Notes/Mechanics/Homebrew Systems/Skills of Alaturmen.md",
    "Game Notes/Mechanics/Homebrew Systems/Mechanics of Plane-walking.md",
    "Game Notes/Mechanics/Homebrew Systems/Homebrew Alchemy System.md",
    "Game Notes/Mechanics/Homebrew Systems/Custom Languages.md",
    "Game Notes/Mechanics/Homebrew Systems/Custom Cultures.md",
    "MEDIA/SUPP/DOCS/GrainIntoGold.pdf",
    "MEDIA/MAPS/WORLD/Thanatos-Player.png",
    "Notes on the Multiverse/Inner/Alaturmen/Texts/Major World Texts",
    "Notes on the Multiverse/Inner/Alaturmen/Places/Coalition Wards",
    "Notes on the Multiverse/Inner/Alaturmen/About People/Nations/The Democratic Combine of Peoples/Local Lore",
    "Notes on the Multiverse/Inner/Alaturmen/Texts/Guild Texts/Bueracracy"
  ]
}