{
  "showUnassigned": false,
  "showAssigned": true,
  "threshold": 0,
  "notificationTimeout": 5,
  "template": "{{commandId}} - {{commandName}} - {{hotkey}}",
  "descriptionOfActions": false,
  "mouseStatistics": {
    "open-with-default-app:show": 1,
    "file-explorer:new-file": 4,
    "workspaces:open-modal": 1,
    "editor:attach-file": 1,
    "app:delete-file": 13,
    "editor:delete-paragraph": 13,
    "graph:open": 6,
    "workspace:undo-close-pane": 12,
    "workspace:close": 12,
    "workspace:close-others": 12,
    "obsidian-dangling-links:show-dangling-links-view": 1,
    "backlink:open": 1,
    "backlink:open-backlinks": 8,
    "backlink:toggle-backlinks-in-document": 1,
    "outgoing-links:open": 1,
    "outgoing-links:open-for-current": 2,
    "editor:rename-heading": 1,
    "map-of-content:rebuild-map-of-content": 2,
    "command-palette:open": 5,
    "map-of-content:show-map-of-content-pane": 2,
    "fantasy-calendar:open-big-fantasy-calendar": 1,
    "obsidian-git:clone-repo": 1
  },
  "keyboardStatistics": {
    "insert-template": 30,
    "switcher:open": 37,
    "editor:open-search": 2,
    "global-search:open": 1,
    "workspace:close": 68,
    "app:go-back": 14,
    "file-explorer:new-file": 4,
    "file-explorer:new-file-in-new-pane": 1,
    "command-palette:open": 1
  }
}